functioncaching/__init__.py
functioncaching/apps.py
functioncaching/middleware.py
functioncaching/sessions.py
django_function_caching-0.2.dist-info/LICENSE
django_function_caching-0.2.dist-info/METADATA
django_function_caching-0.2.dist-info/WHEEL
django_function_caching-0.2.dist-info/top_level.txt
django_function_caching-0.2.dist-info/RECORD
