Metadata-Version: 2.1
Name: django-function-caching
Version: 0.2
Summary: Advanced function caching
Home-page: https://github.com/EralpB/django-function-caching/
Author: Eralp Bayraktar
Author-email: imeralpb@gmail.com
License: MIT
Platform: UNKNOWN
Requires-Dist: Django (>=1.6)
Requires-Dist: django-redis (>=4.11.0)
